copycheck/__about__.py
copycheck/__init__.py
copycheck-1.0.3.dist-info/DESCRIPTION.rst
copycheck-1.0.3.dist-info/METADATA
copycheck-1.0.3.dist-info/RECORD
copycheck-1.0.3.dist-info/WHEEL
copycheck-1.0.3.dist-info/entry_points.txt
copycheck-1.0.3.dist-info/metadata.json
copycheck-1.0.3.dist-info/top_level.txt
