Metadata-Version: 2.0
Name: copycheck
Version: 1.0.3
Summary: Check if files have a proper copyright header.
Home-page: https://github.com/aicis/copycheck
Author: Janus Friis Nielsen
Author-email: jfn@fagidiot.dk
License: MPL 2.0
Keywords: Copyright check
Platform: UNKNOWN
Classifier: Development Status :: 5 - Production/Stable
Classifier: Intended Audience :: Developers
Classifier: License :: OSI Approved :: Mozilla Public License 2.0 (MPL 2.0)
Classifier: Operating System :: OS Independent
Classifier: Programming Language :: Python
Classifier: Programming Language :: Python :: 3.5
Classifier: Programming Language :: Python :: Implementation :: CPython
Classifier: Programming Language :: Python :: Implementation :: PyPy
Classifier: Topic :: Software Development :: Build Tools
Classifier: Topic :: Utilities
Requires-Dist: pathspec
